odoo/addons/fieldservice_sale_agreement_equipment_stock/README.rst
odoo/addons/fieldservice_sale_agreement_equipment_stock/__init__.py
odoo/addons/fieldservice_sale_agreement_equipment_stock/__manifest__.py
odoo/addons/fieldservice_sale_agreement_equipment_stock/i18n/fieldservice_sale_agreement_equipment_stock.pot
odoo/addons/fieldservice_sale_agreement_equipment_stock/i18n/it.po
odoo/addons/fieldservice_sale_agreement_equipment_stock/models/__init__.py
odoo/addons/fieldservice_sale_agreement_equipment_stock/models/stock_move.py
odoo/addons/fieldservice_sale_agreement_equipment_stock/readme/CONTRIBUTORS.md
odoo/addons/fieldservice_sale_agreement_equipment_stock/readme/DESCRIPTION.md
odoo/addons/fieldservice_sale_agreement_equipment_stock/static/description/icon.png
odoo/addons/fieldservice_sale_agreement_equipment_stock/static/description/index.html
odoo/addons/fieldservice_sale_agreement_equipment_stock/tests/__init__.py
odoo/addons/fieldservice_sale_agreement_equipment_stock/tests/test_fsm_sale_agreement_equipment_stock.py
odoo_addon_fieldservice_sale_agreement_equipment_stock-18.0.1.0.0.4.dist-info/METADATA
odoo_addon_fieldservice_sale_agreement_equipment_stock-18.0.1.0.0.4.dist-info/WHEEL
odoo_addon_fieldservice_sale_agreement_equipment_stock-18.0.1.0.0.4.dist-info/top_level.txt
odoo_addon_fieldservice_sale_agreement_equipment_stock-18.0.1.0.0.4.dist-info/RECORD
